indus/__init__.py
indus/feature_engineering.py
indus/test.py
formation_indus_ds_chaimae-0.1.0.dist-info/METADATA
formation_indus_ds_chaimae-0.1.0.dist-info/WHEEL
formation_indus_ds_chaimae-0.1.0.dist-info/top_level.txt
formation_indus_ds_chaimae-0.1.0.dist-info/RECORD
