Metadata-Version: 2.1
Name: formation-indus-ds-chaimae
Version: 0.1.0
Summary: Demonstration pour la formation indus de la data science
Home-page: UNKNOWN
Author: Octo-TOUL
Author-email: 
License: UNKNOWN
Platform: UNKNOWN
Requires-Dist: pandas
Requires-Dist: numpy
Requires-Dist: sklearn
